certipie/__init__.py
certipie/api/__init__.py
certipie/api/cert.py
certipie/api/helpers.py
certipie/api/main.py
certipie/api/schemas.py
certipie/cli/__init__.py
certipie/cli/commands/__init__.py
certipie/cli/commands/auto_cert.py
certipie/cli/commands/completion.py
certipie/cli/commands/csr.py
certipie/cli/commands/rsa.py
certipie/cli/commands/server.py
certipie/cli/main.py
certipie/cli/options.py
certipie/cli/parameters.py
certipie/core.py
certipie/types.py
certipie-0.3.0.dist-info/LICENSE
certipie-0.3.0.dist-info/METADATA
certipie-0.3.0.dist-info/WHEEL
certipie-0.3.0.dist-info/entry_points.txt
certipie-0.3.0.dist-info/RECORD
