Metadata-Version: 2.1
Name: certipie
Version: 0.3.0
Summary: A tool to create certificate signing request and self-signed certificates
Home-page: https://github.com/lewoudar/certipie
License: Apache-2.0
Keywords: certificate,cli,cryptography,fastapi,csr
Author: le_woudar
Author-email: lewoudar@gmail.com
Requires-Python: >=3.9,<4.0
Classifier: Framework :: FastAPI
Classifier: Intended Audience :: Developers
Classifier: License :: OSI Approved :: Apache Software License
Classifier: Operating System :: OS Independent
Classifier: Programming Language :: Python :: 3
Classifier: Programming Language :: Python :: 3.9
Classifier: Programming Language :: Python :: 3.10
Classifier: Programming Language :: Python :: 3.11
Classifier: Programming Language :: Python :: 3.12
Classifier: Topic :: Security :: Cryptography
Classifier: Topic :: Terminals
Requires-Dist: click (>=8.0.3,<9.0.0)
Requires-Dist: click-didyoumean (>=0.3.0,<0.4.0)
Requires-Dist: click-params (>=0.5.0,<0.6.0)
Requires-Dist: cryptography (>=41.0.5,<42.0.0)
Requires-Dist: fastapi (>=0.104.0,<0.105.0)
Requires-Dist: hypercorn (>=0.13.2,<0.14.0)
Requires-Dist: idna (>=3.3,<4.0)
Requires-Dist: python-multipart (>=0.0.5,<0.0.6)
Requires-Dist: shellingham (>=1.4.0,<2.0.0)
Requires-Dist: trio (>=0.20.0,<0.21.0)
Project-URL: Bug Tracker, https://github.com/lewoudar/certipie/issues
Project-URL: Documentation, https://github.com/lewoudar/certipie#readme
Project-URL: Repository, https://github.com/lewoudar/certipie
